ringo_scanner
