Metadata-Version: 2.1
Name: ringo-scanner
Version: 0.1.7
Summary: a framework for scanning the web for vulnerabilities
Home-page: https://github.com/BBleae/RingoScanner
Author: HarukawaSayaka
Author-email: bbleae@outlook.com
License: UNKNOWN
Platform: UNKNOWN
Classifier: Programming Language :: Python :: 3
Classifier: License :: OSI Approved :: MIT License
Classifier: Operating System :: OS Independent
License-File: LICENSE
